fastorm/__init__.py
fastorm/classes.py
fastorm/compat.py
fastorm/query.py
fastorm/utils.py
fastorm-0.0.17.dist-info/LICENSE
fastorm-0.0.17.dist-info/WHEEL
fastorm-0.0.17.dist-info/METADATA
fastorm-0.0.17.dist-info/RECORD
