Metadata-Version: 2.1
Name: fastorm
Version: 0.0.17
Summary: FastORM framework, easy to learn, fast to code
Home-page: https://github.com/luckydonald/fastorm
Author: luckydonald
Author-email: fastorm+code@luckydonald.de
Requires-Python: >=3.10.0
Classifier: Intended Audience :: Information Technology
Classifier: Intended Audience :: System Administrators
Classifier: Operating System :: OS Independent
Classifier: Programming Language :: Python :: 3
Classifier: Programming Language :: Python
Classifier: Topic :: Internet
Classifier: Topic :: Software Development :: Libraries :: Application Frameworks
Classifier: Topic :: Software Development :: Libraries :: Python Modules
Classifier: Topic :: Software Development :: Libraries
Classifier: Topic :: Software Development
Classifier: Typing :: Typed
Classifier: Development Status :: 4 - Beta
Classifier: Environment :: Web Environment
Classifier: Framework :: AsyncIO
Classifier: Intended Audience :: Developers
Classifier: License :: OSI Approved :: MIT License
Classifier: Programming Language :: Python :: 3 :: Only
Classifier: Programming Language :: Python :: 3.7
Classifier: Programming Language :: Python :: 3.10
Requires-Dist: asyncpg
Requires-Dist: luckydonald-utils>=0.83
Requires-Dist: typeguard
Requires-Dist: pydantic
Project-URL: Documentation, https://github.com/luckydonald/fastorm
Provides-Extra: test
